[1,["dbq+QcfN1PnJTWmW+2eED9","75Olr4h01BzYAzLDc6Z+u6","07b1PUcDdK6bXJCDVIygkd"],["_textureSetter","Back_01","Back_02"],["cc.SpriteFrame",["cc.SpriteAtlas",["_name","_spriteFrames"],2,11]],[[1,0,1,2]],[[[{"name":"Back_02","rect":[2,2,72,41],"offset":[0,0],"originalSize":[72,41],"capInsets":[0,0,0,0]}],[0],0,[0],[0],[0]],[[[0,"DerbyBack.plist",[{},"Back_01",6,0,"Back_02",6,1]]],0,0,[0,0],[1,2],[1,2]],[[{"name":"Back_01","rect":[76,2,72,41],"offset":[0,0],"originalSize":[72,41],"rotated":1,"capInsets":[0,0,0,0]}],[0],0,[0],[0],[0]]]]