[1,0,0,[["cc.AnimationClip",["_name","_duration","sample","speed","wrapMode","curveData"],-3]],[[0,0,1,2,3,4,5,7]],[[0,"JackpotWinCoinsParticleAnim",0.9375,16,2,2,{"comps":{"cc.ParticleSystem":{"spriteFrame":[{"frame":0,"value":null},{"frame":0.0625,"value":null},{"frame":0.125,"value":null},{"frame":0.1875,"value":null},{"frame":0.25,"value":null},{"frame":0.3125,"value":null},{"frame":0.375,"value":null},{"frame":0.4375,"value":null},{"frame":0.5,"value":null},{"frame":0.5625,"value":null},{"frame":0.625,"value":null},{"frame":0.6875,"value":null},{"frame":0.75,"value":null},{"frame":0.8125,"value":null},{"frame":0.875,"value":null},{"frame":0.9375,"value":null}]}}}]],0,0,[],[],[]]