[1,["fa6VKq/zVCuqKiutzJrV8H","66HOi6sWlCQZXYZMss/bTe","1bvvaRZuhA5p7gSK2jdg6z","56euJhjxBG26sKFl9HNQu0","48/WL6PExI2b6raPLDBPVy","b9aUevLxhDwZGaZH/90Xsx","1dsmarbP5PxZEYZZsQ3y3v","81LhOLab1FnI0ozKuHAKtz","38L3uziSxDDKyly20NgEZ9","d5VlRtOu9HXZiGzMMPG3Sx","barievVo1PS4U/hmdC1xOV","911kDFj8NIqrpqUFL5hNMJ","65L4DtT9FHgrshlfKQV0Kx","30keWwFuJGLYSh2G8W/+88","73HkecZVtEQ6M/8ZSdW7Hh","8bzRjKfDFHUaZdT7WnM8xb","55e8Ds7VZKw4SsXaKWcaNp","acLXAYe6JLCZdXl+RlMcy7","926ab+cWBGrImMXfMnvnyr","20uyjU/7VNe5YUlp+zlQhc","cetTpMhxFLRoPk5dTvr/e5","7crXcR5ftPRowhAizjGOkr","cdrDs7a41P5q1K/U2agshN","2cT5DUVYRBbo4MthXo7sgb","cbM430eI1BlKsLBPf38zje","80hIfLJuFPcoPDRTfk5tz6","ceQTBJc1tF9JCSAzdzjM71","e0vH9a/EFGLYJR/1jtAzPs","ac8szfUdpAfYv16ipjaSxI","53OieQfg5Hf4625afsJPzM","fbiI9DdK1DspO5gDo0tn6H","57TMzDIRtGepcby9ryvJtS","45OSfGniBGkqQ9ks0V7PrQ"],["value"],[["cc.AnimationClip",["_name","_duration","sample","wrapMode","curveData"],-1,11]],[[0,0,1,2,3,4,5]],[[0,"BDollar_3",1.8,25,2,[{"props":{"opacity":[{"frame":0,"value":255},{"frame":1.32,"value":255},{"frame":1.36,"value":0},{"frame":1.76,"value":0},{"frame":1.8,"value":255}],"width":[{"frame":0,"value":1280}],"height":[{"frame":0,"value":720}]}},"comps",11,[{},"cc.Sprite",11,[{},"spriteFrame",12,[[[{"frame":0},"value",6,0],[{"frame":0.04},"value",6,1],[{"frame":0.08},"value",6,2],[{"frame":0.12},"value",6,3],[{"frame":0.16},"value",6,4],[{"frame":0.2},"value",6,5],[{"frame":0.24},"value",6,6],[{"frame":0.28},"value",6,7],[{"frame":0.32},"value",6,8],[{"frame":0.36},"value",6,9],[{"frame":0.4},"value",6,10],[{"frame":0.44},"value",6,11],[{"frame":0.48},"value",6,12],[{"frame":0.52},"value",6,13],[{"frame":0.56},"value",6,14],[{"frame":0.6},"value",6,15],[{"frame":0.64},"value",6,16],[{"frame":0.68},"value",6,17],[{"frame":0.72},"value",6,18],[{"frame":0.76},"value",6,19],[{"frame":0.8},"value",6,20],[{"frame":0.84},"value",6,21],[{"frame":0.88},"value",6,22],[{"frame":0.92},"value",6,23],[{"frame":0.96},"value",6,24],[{"frame":1},"value",6,25],[{"frame":1.04},"value",6,26],[{"frame":1.08},"value",6,27],[{"frame":1.12},"value",6,28],[{"frame":1.16},"value",6,29],[{"frame":1.2},"value",6,30],[{"frame":1.24},"value",6,31],[{"frame":1.28},"value",6,32],[{"frame":1.76},"value",6,33]],11,11,11,11,11,11,11,11,11,11,11,11,11,11,11,11,11,11,11,11,11,11,11,11,11,11,11,11,11,11,11,11,11,11]]]]]],0,0,[0,0,0,0,0,0,0,0,0,0,0,0,0,0,0,0,0,0,0,0,0,0,0,0,0,0,0,0,0,0,0,0,0,0],[0,0,0,0,0,0,0,0,0,0,0,0,0,0,0,0,0,0,0,0,0,0,0,0,0,0,0,0,0,0,0,0,0,0],[0,1,2,3,4,5,6,7,8,9,10,11,12,13,14,15,16,17,18,19,20,21,22,23,24,25,26,27,28,29,30,31,32,0]]